orient_express/__init__.py
orient_express/deployment.py
orient_express/model_wrapper.py
orient_express/predictors/__init__.py
orient_express/predictors/classification.py
orient_express/predictors/instance_segmentation.py
orient_express/predictors/multi_label_classification.py
orient_express/predictors/object_detection.py
orient_express/predictors/predictor.py
orient_express/predictors/semantic_segmentation.py
orient_express/sklearn_pipeline.py
orient_express/utils/colors.py
orient_express/utils/gs.py
orient_express/utils/image_processor.py
orient_express/utils/paths.py
orient_express/utils/retry.py
orient_express/vertex.py
orient_express-2.1.3.dist-info/METADATA
orient_express-2.1.3.dist-info/WHEEL
orient_express-2.1.3.dist-info/RECORD
