Metadata-Version: 2.4
Name: orient_express
Version: 2.1.3
Summary: A library to simplify model deployment to Vertex AI
Author: Alexey Zankevich
Author-email: alex.zankevich@shiftsmart.com
Requires-Python: >=3.10,<3.13
Classifier: Programming Language :: Python :: 3
Classifier: Programming Language :: Python :: 3.10
Classifier: Programming Language :: Python :: 3.11
Classifier: Programming Language :: Python :: 3.12
Requires-Dist: Pillow (>=10.0.1)
Requires-Dist: gcsfs (>=2024.10.0,<2025.0.0)
Requires-Dist: google-cloud-aiplatform (>=1.0,<2.0)
Requires-Dist: google-cloud-storage (>=3.0,<4.0)
Requires-Dist: onnxruntime (>=1.20,<2.0) ; sys_platform == "darwin" or platform_machine == "aarch64" or platform_machine == "arm64" or sys_platform == "win32" and platform_machine == "ARM64"
Requires-Dist: onnxruntime-gpu (>=1.20,<2.0) ; sys_platform == "linux" and platform_machine == "x86_64" or sys_platform == "win32" and platform_machine == "AMD64"
Requires-Dist: opencv-python-headless (>=4.11.0,<5.0.0)
Requires-Dist: pandas (>=2.0,<3.0)
Requires-Dist: pyyaml (>=6.0,<7.0)
Requires-Dist: scikit-learn (>=1.5.0,<2.0.0)
Requires-Dist: torch (>=2.5.0,<3.0.0)
Requires-Dist: torchvision (>=0.20.0,<0.21.0)
Requires-Dist: xgboost (>=2.0.0,<3.0.0)
